pyskyfire/__init__.py
pyskyfire/common/__init__.py
pyskyfire/common/blocks.py
pyskyfire/common/engine_network.py
pyskyfire/common/fluids.py
pyskyfire/common/results.py
pyskyfire/common/solids.py
pyskyfire/pump/__init__.py
pyskyfire/pump/constants.py
pyskyfire/pump/impeller.py
pyskyfire/pump/plot.py
pyskyfire/pump/pump_cli.py
pyskyfire/pump/utils.py
pyskyfire/regen/__init__.py
pyskyfire/regen/channel_height.py
pyskyfire/regen/contour.py
pyskyfire/regen/cross_section.py
pyskyfire/regen/physics.py
pyskyfire/regen/solver.py
pyskyfire/regen/thrust_chamber.py
pyskyfire/regen/data/theta_e.json
pyskyfire/regen/data/theta_n.json
pyskyfire/skycea/__init__.py
pyskyfire/skycea/aerothermodynamics.py
pyskyfire/skycea/coolant_transport.py
pyskyfire/skycea/data/trans.lib
pyskyfire/turbine/__init__.py
pyskyfire/turbine/temporary_file.py
pyskyfire/viz/__init__.py
pyskyfire/viz/core.py
pyskyfire/viz/embed_stl.py
pyskyfire/viz/export_3d.py
pyskyfire/viz/lookup_tables.py
pyskyfire/viz/plot_common.py
pyskyfire/viz/plot_regen.py
pyskyfire/viz/plot_skycea.py
pyskyfire/viz/report.py
pyskyfire-0.2.1.dist-info/METADATA
pyskyfire-0.2.1.dist-info/WHEEL
pyskyfire-0.2.1.dist-info/licenses/LICENSE
pyskyfire-0.2.1.dist-info/RECORD
