Metadata-Version: 2.4
Name: pyskyfire
Version: 0.2.1
Summary: A Python library for rocket engine simulation and design.
Project-URL: Homepage, https://github.com/ask-hovik/pyskyfire
Project-URL: Issues, https://github.com/ask-hovik/pyskyfire/issues
Author-email: Ask Haugerud Hovik <ask.hovik@gmail.com>
License: MIT License
License-File: LICENSE
Classifier: License :: OSI Approved :: MIT License
Classifier: Operating System :: OS Independent
Classifier: Programming Language :: Python :: 3
Requires-Dist: cea-wrap>=2.0
Requires-Dist: cloudpickle>=3.1
Requires-Dist: coolprop>=7.0
Requires-Dist: gmsh>=4.14
Requires-Dist: numpy>=2.3
Requires-Dist: pandas>=2.3
Requires-Dist: plotly>=6.3
Requires-Dist: pyvis>=0.3
Requires-Dist: scipy>=1.16
Requires-Dist: trimesh>=4.8
